itg_cli/__init__.py
itg_cli/__main__.py
itg_cli/_config.py
itg_cli/_utils.py
itg_cli/commands.py
itg_cli/config_template.toml
itg_cli-1.0.4.dist-info/licenses/LICENSE
itg_cli-1.0.4.dist-info/METADATA
itg_cli-1.0.4.dist-info/WHEEL
itg_cli-1.0.4.dist-info/entry_points.txt
itg_cli-1.0.4.dist-info/top_level.txt
itg_cli-1.0.4.dist-info/RECORD
