Metadata-Version: 2.4
Name: itg-cli
Version: 1.0.4
Author: Lucas Clark
License: MIT License
Project-URL: Repository, https://github.com/lucdar/itg-cli
Keywords: itg,cli,python,itgmania,stepmania
Classifier: Development Status :: 3 - Alpha
Classifier: License :: OSI Approved :: MIT License
Classifier: Programming Language :: Python :: 3.10
Requires-Python: >=3.10
License-File: LICENSE
Requires-Dist: simfile==2.1.1
Requires-Dist: gdown>=5.2.0
Requires-Dist: pyrfc6266>=1.0.2
Requires-Dist: tomlkit>=0.13.2
Requires-Dist: typer>=0.12.5
Dynamic: license-file
